odoo/addons/l10n_fr_state/README.rst
odoo/addons/l10n_fr_state/__init__.py
odoo/addons/l10n_fr_state/__manifest__.py
odoo/addons/l10n_fr_state/pre_init_hook.py
odoo/addons/l10n_fr_state/data/res_country_state_data.yml
odoo/addons/l10n_fr_state/i18n/fr.po
odoo/addons/l10n_fr_state/i18n/l10n_fr_state.pot
odoo/addons/l10n_fr_state/static/description/icon.png
odoo/addons/l10n_fr_state/static/src/img/screenshots/1.png
odoo11_addon_l10n_fr_state-11.0.1.0.0.dist-info/DESCRIPTION.rst
odoo11_addon_l10n_fr_state-11.0.1.0.0.dist-info/METADATA
odoo11_addon_l10n_fr_state-11.0.1.0.0.dist-info/RECORD
odoo11_addon_l10n_fr_state-11.0.1.0.0.dist-info/WHEEL
odoo11_addon_l10n_fr_state-11.0.1.0.0.dist-info/metadata.json
odoo11_addon_l10n_fr_state-11.0.1.0.0.dist-info/top_level.txt
